{
    "/js/altijdsex-nl/app.js": "/js/altijdsex-nl/app.js?id=411da7a8b95871410b12",
    "/css/altijdsex-nl/app.css": "/css/altijdsex-nl/app.css?id=3148dfe75594f9604649",
    "/css/liefdesdate-nl/app.css": "/css/liefdesdate-nl/app.css?id=98ce4b7fb06a437ed4e2",
    "/admin/css/custom.css": "/admin/css/custom.css?id=e5b1ef28dc692a9fe17b",
    "/js/altijdsex-nl/app.js.map": "/js/altijdsex-nl/app.js.map?id=3b94e0a461c55f37a281",
    "/css/altijdsex-nl/app.css.map": "/css/altijdsex-nl/app.css.map?id=01878945e92e30e10e20",
    "/css/liefdesdate-nl/app.css.map": "/css/liefdesdate-nl/app.css.map?id=43f97138e90ce354f051",
    "/admin/css/custom.css.map": "/admin/css/custom.css.map?id=c26ac62406f6a8ff1023",
    "/js/liefdesdate-nl/app.js": "/js/liefdesdate-nl/app.js?id=25f920a4794780ba4454",
    "/js/liefdesdate-nl/app.js.map": "/js/liefdesdate-nl/app.js.map?id=eb0b39ed377e041ef2b4",
    "/admin/js/custom-force.js": "/admin/js/custom-force.js?id=d4a33427b8028c291b5e",
    "/admin/js/custom-force.js.map": "/admin/js/custom-force.js.map?id=08587388f39907f2463f",
    "/js/lp.js": "/js/lp.js?id=59ef54edadca7ec11409",
    "/js/lp.js.map": "/js/lp.js.map?id=3e58a8bfef2d08d2ab1d",
    "/js/lps/ads/lp2.js": "/js/lps/ads/lp2.js?id=013a3ba45b7b99831b73",
    "/js/lps/ads/lp2.js.map": "/js/lps/ads/lp2.js.map?id=bec3050ba18e45a13776",
    "/js/lps/ads/lp1.js": "/js/lps/ads/lp1.js?id=b5484d297dd5d64df37d",
    "/js/lps/ads/lp1.js.map": "/js/lps/ads/lp1.js.map?id=51505d145e2f3733bce9",
    "/admin/css/plugins.css": "/admin/css/plugins.css?id=45a84309d4c66993673d",
    "/admin/js/plugins-force.js": "/admin/js/plugins-force.js?id=e8da6036ef883032d432"
}
