{
    "/js/app.js": "/js/app.js?id=4cee43cb56129f696b0a",
    "/css/altijdsex-nl/app.css": "/css/altijdsex-nl/app.css?id=203539bd222a94d3b1ca",
    "/css/whitelabel-nl/app.css": "/css/whitelabel-nl/app.css?id=83faef625a330bac9574",
    "/admin/css/custom.css": "/admin/css/custom.css?id=e46e1be12e43f2aa95d8",
    "/js/app.js.map": "/js/app.js.map?id=e9f8b7343487a9c2171f",
    "/css/altijdsex-nl/app.css.map": "/css/altijdsex-nl/app.css.map?id=43704d66bb8533e605cf",
    "/css/whitelabel-nl/app.css.map": "/css/whitelabel-nl/app.css.map?id=55c20d48bcaf4fc58efb",
    "/admin/css/custom.css.map": "/admin/css/custom.css.map?id=8e8b3461dcbbc7b2fe9c",
    "/admin/js/custom-force.js": "/admin/js/custom-force.js?id=5432c1cff9e322a5fdbb",
    "/admin/js/custom-force.js.map": "/admin/js/custom-force.js.map?id=fa886f31e3732f42f9f9",
    "/js/lp.js": "/js/lp.js?id=47170532ffdb47e8b8e2",
    "/js/lp.js.map": "/js/lp.js.map?id=daabec2d64c047c19a0b",
    "/js/lps/ads/lp2.js": "/js/lps/ads/lp2.js?id=595acd16a83f95a6b6e3",
    "/js/lps/ads/lp2.js.map": "/js/lps/ads/lp2.js.map?id=6f6f15cc599b5497b522",
    "/js/lps/ads/lp1.js": "/js/lps/ads/lp1.js?id=4a7605ed4c459fae1099",
    "/js/lps/ads/lp1.js.map": "/js/lps/ads/lp1.js.map?id=e0377229db2771a2f908",
    "/admin/css/plugins.css": "/admin/css/plugins.css?id=45a84309d4c66993673d",
    "/admin/js/plugins-force.js": "/admin/js/plugins-force.js?id=e8da6036ef883032d432"
}
